odoo/addons/account_in_payment/README.rst
odoo/addons/account_in_payment/__init__.py
odoo/addons/account_in_payment/__manifest__.py
odoo/addons/account_in_payment/i18n/account_in_payment.pot
odoo/addons/account_in_payment/i18n/it.po
odoo/addons/account_in_payment/i18n/lv.po
odoo/addons/account_in_payment/i18n/pt.po
odoo/addons/account_in_payment/i18n/pt_BR.po
odoo/addons/account_in_payment/models/__init__.py
odoo/addons/account_in_payment/models/account_move.py
odoo/addons/account_in_payment/readme/CONTRIBUTORS.md
odoo/addons/account_in_payment/readme/DESCRIPTION.md
odoo/addons/account_in_payment/static/description/icon.png
odoo/addons/account_in_payment/static/description/index.html
odoo/addons/account_in_payment/tests/__init__.py
odoo/addons/account_in_payment/tests/test_bank_account_reconcile.py
odoo_addon_account_in_payment-18.0.1.0.0.4.dist-info/METADATA
odoo_addon_account_in_payment-18.0.1.0.0.4.dist-info/WHEEL
odoo_addon_account_in_payment-18.0.1.0.0.4.dist-info/top_level.txt
odoo_addon_account_in_payment-18.0.1.0.0.4.dist-info/RECORD
