Metadata-Version: 2.1
Name: odoo-addon-account_in_payment
Version: 18.0.1.0.0.4
Requires-Python: >=3.10
Requires-Dist: odoo-addon-account_reconcile_oca==18.0.*
Requires-Dist: odoo==18.0.*
Summary: This module enables in-payment mode for your accounting
Home-page: https://github.com/OCA/account-reconcile
License: AGPL-3
Author: Dixmit,Odoo Community Association (OCA)
Author-email: support@odoo-community.org
Classifier: Programming Language :: Python
Classifier: Framework :: Odoo
Classifier: Framework :: Odoo :: 18.0
Classifier: License :: OSI Approved :: GNU Affero General Public License v3
